mk8dx/__init__.py
mk8dx/data.py
mk8dx/mogi.py
mk8dx/race.py
mk8dx/rank.py
mk8dx/lounge_api/__init__.py
mk8dx/lounge_api/bonus.py
mk8dx/lounge_api/leaderboard.py
mk8dx/lounge_api/lounge_api.py
mk8dx/lounge_api/penalty.py
mk8dx/lounge_api/player.py
mk8dx/lounge_api/player_details.py
mk8dx/lounge_api/player_list.py
mk8dx/lounge_api/rank.py
mk8dx/lounge_api/table_details.py
mk8dx-1.2.3.dist-info/METADATA
mk8dx-1.2.3.dist-info/WHEEL
mk8dx-1.2.3.dist-info/top_level.txt
mk8dx-1.2.3.dist-info/RECORD
