Metadata-Version: 2.1
Name: mk8dx
Version: 1.2.3
Summary: To help to develop something about mk8dx
Home-page: https://github.com/sheat-git/mk8dx.py
Author: sheat
License: MIT
Requires-Dist: aiohttp ==3.8.1
Requires-Dist: jaconv ==0.3
Requires-Dist: python-dateutil ==2.8.2
